sentry_faust_integration/__init__.py
sentry_faust_integration/main.py
sentry_faust_integration-0.1.3.dist-info/LICENSE
sentry_faust_integration-0.1.3.dist-info/WHEEL
sentry_faust_integration-0.1.3.dist-info/METADATA
sentry_faust_integration-0.1.3.dist-info/RECORD
