Metadata-Version: 2.1
Name: sentry-faust-integration
Version: 0.1.3
Summary: 
Author: dmitry
Author-email: dmitrysmirnov931@gmail.com
Requires-Python: >=3.9,<4.0
Classifier: Programming Language :: Python :: 3
Classifier: Programming Language :: Python :: 3.10
Classifier: Programming Language :: Python :: 3.9
Requires-Dist: faust (>=1.10.4,<2.0.0)
Requires-Dist: sentry-sdk (>=1.5.0,<2.0.0)
